executor_exporter/__init__.py
executor_exporter/executors.py
executor_exporter/exporter.py
executor_exporter/proxy.py
executor_exporter-0.1.2.dist-info/LICENSE
executor_exporter-0.1.2.dist-info/WHEEL
executor_exporter-0.1.2.dist-info/METADATA
executor_exporter-0.1.2.dist-info/RECORD
