Metadata-Version: 2.1
Name: executor-exporter
Version: 0.1.2
Summary: A Prometheus exporter for Python concurrent.futures executors
Home-page: https://github.com/ygormutti/executor-exporter
License: Apache-2.0
Keywords: ThreadPoolExecutor,ProcessPoolExecutor,prometheus,metrics,exporter
Author: Ygor Mutti
Author-email: ygormutti@gmail.com
Requires-Python: >=3.8,<4.0
Classifier: License :: OSI Approved :: Apache Software License
Classifier: Programming Language :: Python :: 3
Classifier: Programming Language :: Python :: 3.8
Classifier: Programming Language :: Python :: 3.9
Requires-Dist: prometheus-client (>=0.11.0,<0.12.0)
Project-URL: Repository, https://github.com/ygormutti/executor-exporter
